hjklhjkvv/__init__.py
hjklhjkvv/py.typed
hjklhjkvv/sum.py
hjklhjkvv-5.0.dist-info/LICENSE
hjklhjkvv-5.0.dist-info/METADATA
hjklhjkvv-5.0.dist-info/WHEEL
hjklhjkvv-5.0.dist-info/top_level.txt
hjklhjkvv-5.0.dist-info/RECORD
