Metadata-Version: 2.1
Name: hjklhjkvv
Version: 5.0
Summary: ---------
Home-page: https://github.com/xvfgc/hjklhjkvv
Author: xvfgc
License: MIT
Requires-Python: >=3.10
License-File: LICENSE
Requires-Dist: numpy
